tree_scribe/__init__.py
tree_scribe/filters.py
tree_scribe/main.py
tree_scribe-1.0.2.dist-info/METADATA
tree_scribe-1.0.2.dist-info/WHEEL
tree_scribe-1.0.2.dist-info/entry_points.txt
tree_scribe-1.0.2.dist-info/top_level.txt
tree_scribe-1.0.2.dist-info/RECORD
