Metadata-Version: 2.1
Name: tree-scribe
Version: 1.0.2
Summary: Generate and export directory tree structures with optional color output.
Home-page: https://github.com/mamad-1999/tree-scribe
Author: mamad1999
Author-email: www.mmhmdmm83@gmail.com
License: UNKNOWN
Platform: UNKNOWN
Classifier: Programming Language :: Python :: 3
Classifier: License :: OSI Approved :: MIT License
Classifier: Operating System :: OS Independent
Requires-Python: >=3.6
Requires-Dist: colorama
